MANIFEST.in
requirements.txt
setup.py
cargo_users/__init__.py
cargo_users/decorators.py
cargo_users/exceptions.py
cargo_users/fields.py
cargo_users/managers.py
cargo_users/models.py
cargo_users/oauth.py
cargo_users/plans.py
cargo_users/utils.py
cargo_users.egg-info/PKG-INFO
cargo_users.egg-info/SOURCES.txt
cargo_users.egg-info/dependency_links.txt
cargo_users.egg-info/requires.txt
cargo_users.egg-info/top_level.txt