Metadata-Version: 1.0
Name: cargo-users
Version: 0.1.5
Summary: User models and controllers based on the Cargo ORM.
Home-page: https://github.com/jaredlunde/cargo-users
Author: Jared Lunde
Author-email: jared.lunde@gmail.com
License: MIT
Platform: UNKNOWN
